README.md
setup.py
crypto_exchanges_clients/BaseExchange.py
crypto_exchanges_clients/Binance.py
crypto_exchanges_clients/Bitget.py
crypto_exchanges_clients/Bybit.py
crypto_exchanges_clients/Coinbase.py
crypto_exchanges_clients/Okx.py
crypto_exchanges_clients/__init__.py
crypto_exchanges_clients/utils.py
crypto_exchanges_clients.egg-info/PKG-INFO
crypto_exchanges_clients.egg-info/SOURCES.txt
crypto_exchanges_clients.egg-info/dependency_links.txt
crypto_exchanges_clients.egg-info/requires.txt
crypto_exchanges_clients.egg-info/top_level.txt