Metadata-Version: 2.1
Name: crypto_exchanges_clients
Version: 0.0.2
Summary: client for various crypto exchanges
Author: fleecy
Requires-Dist: aiohttp>=3.8.0
